pretty_little_summary/__init__.py
pretty_little_summary/api.py
pretty_little_summary/core.py
pretty_little_summary/descriptor_registry.py
pretty_little_summary/descriptor_utils.py
pretty_little_summary/file_loader.py
pretty_little_summary/py.typed
pretty_little_summary/synthesizer.py
pretty_little_summary/adapters/__init__.py
pretty_little_summary/adapters/_base.py
pretty_little_summary/adapters/altair.py
pretty_little_summary/adapters/async_adapter.py
pretty_little_summary/adapters/attrs_adapter.py
pretty_little_summary/adapters/bokeh_adapter.py
pretty_little_summary/adapters/callables.py
pretty_little_summary/adapters/collections.py
pretty_little_summary/adapters/datetime_adapter.py
pretty_little_summary/adapters/errors.py
pretty_little_summary/adapters/generic.py
pretty_little_summary/adapters/h5py_adapter.py
pretty_little_summary/adapters/io_adapter.py
pretty_little_summary/adapters/ipython_display.py
pretty_little_summary/adapters/jax_adapter.py
pretty_little_summary/adapters/matplotlib.py
pretty_little_summary/adapters/networkx.py
pretty_little_summary/adapters/numpy_adapter.py
pretty_little_summary/adapters/pandas.py
pretty_little_summary/adapters/pathlib_adapter.py
pretty_little_summary/adapters/pil_adapter.py
pretty_little_summary/adapters/plotly_adapter.py
pretty_little_summary/adapters/polars.py
pretty_little_summary/adapters/primitives.py
pretty_little_summary/adapters/pyarrow_adapter.py
pretty_little_summary/adapters/pydantic.py
pretty_little_summary/adapters/pytorch.py
pretty_little_summary/adapters/regex_adapter.py
pretty_little_summary/adapters/requests.py
pretty_little_summary/adapters/scipy_sparse_adapter.py
pretty_little_summary/adapters/seaborn_adapter.py
pretty_little_summary/adapters/sklearn.py
pretty_little_summary/adapters/sklearn_pipeline.py
pretty_little_summary/adapters/statsmodels_adapter.py
pretty_little_summary/adapters/structured.py
pretty_little_summary/adapters/tensorflow_adapter.py
pretty_little_summary/adapters/text_formats.py
pretty_little_summary-0.1.1.dist-info/METADATA
pretty_little_summary-0.1.1.dist-info/WHEEL
pretty_little_summary-0.1.1.dist-info/licenses/LICENSE
pretty_little_summary-0.1.1.dist-info/RECORD
