Metadata-Version: 2.4
Name: pretty-little-summary
Version: 0.1.1
Summary: Automatic structured summaries of Python objects - DataFrames, arrays, models, and more
Project-URL: Homepage, https://github.com/dwootton/pretty-little-summary
Project-URL: Repository, https://github.com/dwootton/pretty-little-summary
Project-URL: Issues, https://github.com/dwootton/pretty-little-summary/issues
Project-URL: Documentation, https://dwootton.github.io/pretty-little-summary
Author-email: Dylan <wootton.dylan@gmail.com>
License: MIT License
License-File: LICENSE
Keywords: data-science,introspection,jupyter,metadata,summarization
Classifier: Development Status :: 3 - Alpha
Classifier: Intended Audience :: Developers
Classifier: License :: OSI Approved :: MIT License
Classifier: Programming Language :: Python :: 3.10
Classifier: Programming Language :: Python :: 3.11
Classifier: Programming Language :: Python :: 3.12
Classifier: Topic :: Scientific/Engineering
Classifier: Topic :: Software Development :: Libraries :: Python Modules
Requires-Python: >=3.10
Provides-Extra: all
Requires-Dist: altair>=5.0.0; extra == 'all'
Requires-Dist: attrs>=23.0.0; extra == 'all'
Requires-Dist: bokeh>=3.0.0; extra == 'all'
Requires-Dist: h5py>=3.9.0; extra == 'all'
Requires-Dist: ipython>=8.0.0; extra == 'all'
Requires-Dist: jax>=0.4.0; extra == 'all'
Requires-Dist: matplotlib>=3.8.0; extra == 'all'
Requires-Dist: networkx>=3.0.0; extra == 'all'
Requires-Dist: numpy>=1.24.0; extra == 'all'
Requires-Dist: pandas>=2.0.0; extra == 'all'
Requires-Dist: pillow>=10.0.0; extra == 'all'
Requires-Dist: plotly>=5.0.0; extra == 'all'
Requires-Dist: polars>=0.20.0; extra == 'all'
Requires-Dist: pyarrow>=12.0.0; extra == 'all'
Requires-Dist: pydantic>=2.0.0; extra == 'all'
Requires-Dist: requests>=2.31.0; extra == 'all'
Requires-Dist: scikit-learn>=1.4.0; extra == 'all'
Requires-Dist: scipy>=1.10.0; extra == 'all'
Requires-Dist: seaborn>=0.13.0; extra == 'all'
Requires-Dist: statsmodels>=0.14.0; extra == 'all'
Requires-Dist: tensorflow>=2.0.0; extra == 'all'
Requires-Dist: torch>=2.0.0; extra == 'all'
Requires-Dist: xarray>=2024.0.0; extra == 'all'
Provides-Extra: altair
Requires-Dist: altair>=5.0.0; extra == 'altair'
Provides-Extra: attrs
Requires-Dist: attrs>=23.0.0; extra == 'attrs'
Provides-Extra: bokeh
Requires-Dist: bokeh>=3.0.0; extra == 'bokeh'
Provides-Extra: data
Requires-Dist: numpy>=1.24.0; extra == 'data'
Requires-Dist: pandas>=2.0.0; extra == 'data'
Requires-Dist: polars>=0.20.0; extra == 'data'
Requires-Dist: pyarrow>=12.0.0; extra == 'data'
Provides-Extra: dev
Requires-Dist: build>=1.2.0; extra == 'dev'
Requires-Dist: mypy>=1.8.0; extra == 'dev'
Requires-Dist: pytest-asyncio>=0.23.0; extra == 'dev'
Requires-Dist: pytest-cov>=4.1.0; extra == 'dev'
Requires-Dist: pytest>=8.0.0; extra == 'dev'
Requires-Dist: ruff>=0.1.0; extra == 'dev'
Requires-Dist: twine>=5.0.0; extra == 'dev'
Provides-Extra: h5py
Requires-Dist: h5py>=3.9.0; extra == 'h5py'
Provides-Extra: ipython
Requires-Dist: ipython>=8.0.0; extra == 'ipython'
Provides-Extra: jax
Requires-Dist: jax>=0.4.0; extra == 'jax'
Provides-Extra: matplotlib
Requires-Dist: matplotlib>=3.8.0; extra == 'matplotlib'
Provides-Extra: ml
Requires-Dist: jax>=0.4.0; extra == 'ml'
Requires-Dist: scikit-learn>=1.4.0; extra == 'ml'
Requires-Dist: scipy>=1.10.0; extra == 'ml'
Requires-Dist: statsmodels>=0.14.0; extra == 'ml'
Requires-Dist: tensorflow>=2.0.0; extra == 'ml'
Requires-Dist: torch>=2.0.0; extra == 'ml'
Provides-Extra: networkx
Requires-Dist: networkx>=3.0.0; extra == 'networkx'
Provides-Extra: numpy
Requires-Dist: numpy>=1.24.0; extra == 'numpy'
Provides-Extra: pandas
Requires-Dist: pandas>=2.0.0; extra == 'pandas'
Provides-Extra: pillow
Requires-Dist: pillow>=10.0.0; extra == 'pillow'
Provides-Extra: plotly
Requires-Dist: plotly>=5.0.0; extra == 'plotly'
Provides-Extra: polars
Requires-Dist: polars>=0.20.0; extra == 'polars'
Provides-Extra: pyarrow
Requires-Dist: pyarrow>=12.0.0; extra == 'pyarrow'
Provides-Extra: pydantic
Requires-Dist: pydantic>=2.0.0; extra == 'pydantic'
Provides-Extra: pytorch
Requires-Dist: torch>=2.0.0; extra == 'pytorch'
Provides-Extra: requests
Requires-Dist: requests>=2.31.0; extra == 'requests'
Provides-Extra: science
Requires-Dist: h5py>=3.9.0; extra == 'science'
Requires-Dist: networkx>=3.0.0; extra == 'science'
Requires-Dist: scipy>=1.10.0; extra == 'science'
Requires-Dist: xarray>=2024.0.0; extra == 'science'
Provides-Extra: scipy
Requires-Dist: scipy>=1.10.0; extra == 'scipy'
Provides-Extra: seaborn
Requires-Dist: seaborn>=0.13.0; extra == 'seaborn'
Provides-Extra: sklearn
Requires-Dist: scikit-learn>=1.4.0; extra == 'sklearn'
Provides-Extra: statsmodels
Requires-Dist: statsmodels>=0.14.0; extra == 'statsmodels'
Provides-Extra: tensorflow
Requires-Dist: tensorflow>=2.0.0; extra == 'tensorflow'
Provides-Extra: viz
Requires-Dist: altair>=5.0.0; extra == 'viz'
Requires-Dist: bokeh>=3.0.0; extra == 'viz'
Requires-Dist: matplotlib>=3.8.0; extra == 'viz'
Requires-Dist: pillow>=10.0.0; extra == 'viz'
Requires-Dist: plotly>=5.0.0; extra == 'viz'
Requires-Dist: seaborn>=0.13.0; extra == 'viz'
Provides-Extra: web
Requires-Dist: requests>=2.31.0; extra == 'web'
Provides-Extra: xarray
Requires-Dist: xarray>=2024.0.0; extra == 'xarray'
